letmedoit/README.md
letmedoit/__init__.py
letmedoit/autoassist.py
letmedoit/autobuilder.py
letmedoit/automath.py
letmedoit/autoretriever.py
letmedoit/chatgpt.py
letmedoit/codey.py
letmedoit/commandprompt.py
letmedoit/config.py
letmedoit/eTextEdit.py
letmedoit/geminipro.py
letmedoit/geminiprovision.py
letmedoit/health_check.py
letmedoit/main.py
letmedoit/ollamachat.py
letmedoit/package_name.txt
letmedoit/palm2.py
letmedoit/requirements.txt
letmedoit/systemtray.py
letmedoit/audio/notification1.mp3
letmedoit/audio/notification1_mild.mp3
letmedoit/audio/notification2.mp3
letmedoit/audio/notification2_mild.mp3
letmedoit/files/Readme.md
letmedoit/history/Readme.md
letmedoit/icons/CyberTask.ico
letmedoit/icons/CyberTask.png
letmedoit/icons/GeminiPro.ico
letmedoit/icons/GeminiPro.png
letmedoit/icons/LetMeDoIt.ico
letmedoit/icons/LetMeDoIt.png
letmedoit/icons/MyHand.ico
letmedoit/icons/MyHand.png
letmedoit/icons/TaskWiz.ico
letmedoit/icons/TaskWiz.png
letmedoit/icons/systemtray.ico
letmedoit/icons/systemtray.png
letmedoit/macOS_service/LetMeDoIt_Download_workflow/Contents/Info.plist
letmedoit/macOS_service/LetMeDoIt_Download_workflow/Contents/document.wflow
letmedoit/macOS_service/LetMeDoIt_Download_workflow/Contents/QuickLook/Thumbnail.png
letmedoit/macOS_service/LetMeDoIt_Explanation_workflow/Contents/Info.plist
letmedoit/macOS_service/LetMeDoIt_Explanation_workflow/Contents/document.wflow
letmedoit/macOS_service/LetMeDoIt_Explanation_workflow/Contents/QuickLook/Thumbnail.png
letmedoit/macOS_service/LetMeDoIt_Files_workflow/Contents/Info.plist
letmedoit/macOS_service/LetMeDoIt_Files_workflow/Contents/document.wflow
letmedoit/macOS_service/LetMeDoIt_Files_workflow/Contents/QuickLook/Thumbnail.png
letmedoit/macOS_service/LetMeDoIt_Pronounce_workflow/Contents/Info.plist
letmedoit/macOS_service/LetMeDoIt_Pronounce_workflow/Contents/document.wflow
letmedoit/macOS_service/LetMeDoIt_Pronounce_workflow/Contents/QuickLook/Thumbnail.png
letmedoit_android-0.0.98.dist-info/METADATA
letmedoit_android-0.0.98.dist-info/WHEEL
letmedoit_android-0.0.98.dist-info/entry_points.txt
letmedoit_android-0.0.98.dist-info/top_level.txt
letmedoit_android-0.0.98.dist-info/RECORD
